oneHTTP/__init__.py
oneHTTP/onehttp.py
onehttp-1.0.0.dist-info/METADATA
onehttp-1.0.0.dist-info/WHEEL
onehttp-1.0.0.dist-info/top_level.txt
onehttp-1.0.0.dist-info/RECORD
